Workbook

Sheet Control_Panel
A1: Marketing Performance ROI – Control Panel
A3: Scenario | B3: Base | D3: Scenario Library
A5: Global Inputs | D5: Scenario | E5: Spend Mult | F5: Conv Mult | G5: AOV Mult
A6: Base Monthly Spend ($) | B6: 40000 | D6: Base | E6: 1 | F6: 1 | G6: 1
A7: Base Conversion Rate | B7: 0.04 | D7: Aggressive | E7: 1.2 | F7: 1.1 | G7: 1.02
A8: Base AOV ($) | B8: 80 | D8: Conservative | E8: 0.85 | F8: 0.92 | G8: 0.98
A9: Gross Margin % | B9: 0.35 | D9: (Used by dropdown & lookups)
A10: Target ROAS | B10: 3.5
A11: CAC Target ($) | B11: 25
A12: Base ROAS | B12: 3.6
A13: Scenario Multipliers (auto) | D13: Effective Scenario Inputs (auto)
A14: Spend Mult | B14: =INDEX($E$6:$E$8, MATCH($B$3, $D$6:$D$8, 0)) | D14: Effective Spend ($) | E14: =B6*B14
A15: Conv Mult | B15: =INDEX($F$6:$F$8, MATCH($B$3, $D$6:$D$8, 0)) | D15: Effective Conv Rate | E15: =B7*B15
A16: AOV Mult | B16: =INDEX($G$6:$G$8, MATCH($B$3, $D$6:$D$8, 0)) | D16: Effective AOV ($) | E16: =B8*B16
D17: Effective ROAS (auto) | E17: =B12*(1+(B15-1)*0.6)

Sheet Executive_Dashboard
A1: Marketing ROI Executive Dashboard
A3: Selected Scenario: | B3: =Control_Panel!B3
A5: Spend | E5: Revenue
A6: =Control_Panel!E14 | E6: =Control_Panel!E14*Control_Panel!E17
A9: ROAS | E9: Net Profit
A10: =Control_Panel!E17 | E10: =(Control_Panel!E14*Control_Panel!E17*Control_Panel!B9)-Control_Panel!E14
A14: KPI Status
A15: Metric | B15: Actual | C15: Target | D15: Variance | E15: Status
A16: ROAS | B16: =Control_Panel!E17 | C16: =Control_Panel!B10 | D16: =B16-C16 | E16: =IF(B16>=C16,"On Track","Below Target")
A17: Net Profit | B17: =(Control_Panel!E14*Control_Panel!E17*Control_Panel!B9)-Control_Panel!E14 | C17: 0 | D17: =B17-C17 | E17: =IF(B17>=C17,"On Track","Below Target")

Sheet Channel_Drilldown
A1: Channel Performance Drilldown
A2: Channel | B2: Spend | C2: Revenue | D2: ROAS | E2: Target ROAS | F2: Variance | G2: Status
A3: Google Ads | B3: 22000 | C3: 82000 | D3: =C3/B3 | E3: 3.5 | F3: =D3-E3 | G3: =IF(D3>=E3,"Above Target","Below Target")
A4: Facebook Ads | B4: 15000 | C4: 42000 | D4: =C4/B4 | E4: 3 | F4: =D4-E4 | G4: =IF(D4>=E4,"Above Target","Below Target")
A5: TikTok Ads | B5: 8000 | C5: 22000 | D5: =C5/B5 | E5: 2.8 | F5: =D5-E5 | G5: =IF(D5>=E5,"Above Target","Below Target")
A6: Email | B6: 4000 | C6: 21000 | D6: =C6/B6 | E6: 4 | F6: =D6-E6 | G6: =IF(D6>=E6,"Above Target","Below Target")

Sheet Forecast
A1: Revenue Forecast (Monthly)
A2: Month | B2: Spend | C2: Revenue
A3: Jan | B3: 30000 | C3: 102000
A4: Feb | B4: 32000 | C4: 108800
A5: Mar | B5: 34000 | C5: 115600
A6: Apr | B6: 36000 | C6: 122400
A7: May | B7: 38000 | C7: 129200
A8: Jun | B8: 40000 | C8: 136000
A9: Jul | B9: 42000 | C9: 142800
A10: Aug | B10: 41000 | C10: 139400
A11: Sep | B11: 39000 | C11: 132600
A12: Oct | B12: 37000 | C12: 125800
A13: Nov | B13: 35000 | C13: 119000
A14: Dec | B14: 33000 | C14: 112200

Sheet Sensitivity
A1: Sensitivity Analysis (Conversion Rate vs Net Profit)
A2: Conversion Rate | B2: Net Profit (auto)
A3: 0.03 | B3: =(Control_Panel!E14*(Control_Panel!B12*(1+((A3/Control_Panel!B7)-1)*0.6))*Control_Panel!B9)-Control_Panel!E14
A4: 0.035 | B4: =(Control_Panel!E14*(Control_Panel!B12*(1+((A4/Control_Panel!B7)-1)*0.6))*Control_Panel!B9)-Control_Panel!E14
A5: 0.04 | B5: =(Control_Panel!E14*(Control_Panel!B12*(1+((A5/Control_Panel!B7)-1)*0.6))*Control_Panel!B9)-Control_Panel!E14
A6: 0.045 | B6: =(Control_Panel!E14*(Control_Panel!B12*(1+((A6/Control_Panel!B7)-1)*0.6))*Control_Panel!B9)-Control_Panel!E14
A7: 0.05 | B7: =(Control_Panel!E14*(Control_Panel!B12*(1+((A7/Control_Panel!B7)-1)*0.6))*Control_Panel!B9)-Control_Panel!E14
A8: 0.055 | B8: =(Control_Panel!E14*(Control_Panel!B12*(1+((A8/Control_Panel!B7)-1)*0.6))*Control_Panel!B9)-Control_Panel!E14

Sheet Executive_Decision
A1: Executive Decision Summary
A3: Recommended Scenario | C3: Why this works
A4: =Control_Panel!B3 | C4: Meets ROAS target, maximizes profit, and supports scalable growth.
A7: Key Numbers
A8: Metric | B8: Value
A9: Spend | B9: =Control_Panel!E14
A10: Revenue | B10: =Control_Panel!E14*Control_Panel!E17
A11: ROAS | B11: =Control_Panel!E17
A12: Net Profit | B12: =(Control_Panel!E14*Control_Panel!E17*Control_Panel!B9)-Control_Panel!E14
